simple_fast_regex-0.4.0.dist-info/METADATA
simple_fast_regex-0.4.0.dist-info/WHEEL
simple_fast_regex.libs/libgcc_s-b5472b99.so.1
simple_fast_regex/__init__.py
simple_fast_regex/__init__.pyi
simple_fast_regex/py.typed
simple_fast_regex/simple_fast_regex.cpython-39-i386-linux-gnu.so
simple_fast_regex-0.4.0.dist-info/RECORD
