Metadata-Version: 2.3
Name: simple_fast_regex
Version: 0.4.0
Classifier: Programming Language :: Rust
Classifier: Programming Language :: Python :: Implementation :: CPython
Classifier: Programming Language :: Python :: Implementation :: PyPy
Summary: A fast regular expression library for Python and Rust
Author-email: Pedro Ribeiro <pedro.ribeiro@soliduslabs.com>
Requires-Python: >=3.8
